<annotation>
  <filename>18--Concerts/18_Concerts_Concerts_18_703.jpg</filename>
  <size>
    <width>1024</width>
    <height>768</height>
    <depth>3</depth>
  </size>
  <object>
    <name>face</name>
    <pose>Unspecified</pose>
    <truncated>0</truncated>
    <difficult>0</difficult>
    <bndbox>
      <xmin>363</xmin>
      <ymin>259</ymin>
      <xmax>409</xmax>
      <ymax>292</ymax>
    </bndbox>
  </object>
  <object>
    <name>face</name>
    <pose>Unspecified</pose>
    <truncated>0</truncated>
    <difficult>0</difficult>
    <bndbox>
      <xmin>184</xmin>
      <ymin>292</ymin>
      <xmax>189</xmax>
      <ymax>297</ymax>
    </bndbox>
  </object>
  <object>
    <name>face</name>
    <pose>Unspecified</pose>
    <truncated>0</truncated>
    <difficult>0</difficult>
    <bndbox>
      <xmin>301</xmin>
      <ymin>297</ymin>
      <xmax>308</xmax>
      <ymax>303</ymax>
    </bndbox>
  </object>
</annotation>
