<annotation>
  <filename>31--Waiter_Waitress/31_Waiter_Waitress_Waiter_Waitress_31_855.jpg</filename>
  <size>
    <width>1024</width>
    <height>683</height>
    <depth>3</depth>
  </size>
  <object>
    <name>face</name>
    <pose>Unspecified</pose>
    <truncated>0</truncated>
    <difficult>0</difficult>
    <bndbox>
      <xmin>268</xmin>
      <ymin>104</ymin>
      <xmax>434</xmax>
      <ymax>230</ymax>
    </bndbox>
  </object>
  <object>
    <name>face</name>
    <pose>Unspecified</pose>
    <truncated>0</truncated>
    <difficult>0</difficult>
    <bndbox>
      <xmin>476</xmin>
      <ymin>208</ymin>
      <xmax>582</xmax>
      <ymax>268</ymax>
    </bndbox>
  </object>
  <object>
    <name>face</name>
    <pose>Unspecified</pose>
    <truncated>0</truncated>
    <difficult>0</difficult>
    <bndbox>
      <xmin>744</xmin>
      <ymin>132</ymin>
      <xmax>834</xmax>
      <ymax>196</ymax>
    </bndbox>
  </object>
</annotation>
