<annotation>
  <filename>25--Soldier_Patrol/25_Soldier_Patrol_Soldier_Patrol_25_476.jpg</filename>
  <size>
    <width>1024</width>
    <height>677</height>
    <depth>3</depth>
  </size>
  <object>
    <name>face</name>
    <pose>Unspecified</pose>
    <truncated>0</truncated>
    <difficult>0</difficult>
    <bndbox>
      <xmin>166</xmin>
      <ymin>199</ymin>
      <xmax>218</xmax>
      <ymax>239</ymax>
    </bndbox>
  </object>
  <object>
    <name>face</name>
    <pose>Unspecified</pose>
    <truncated>0</truncated>
    <difficult>0</difficult>
    <bndbox>
      <xmin>472</xmin>
      <ymin>224</ymin>
      <xmax>530</xmax>
      <ymax>269</ymax>
    </bndbox>
  </object>
  <object>
    <name>face</name>
    <pose>Unspecified</pose>
    <truncated>0</truncated>
    <difficult>0</difficult>
    <bndbox>
      <xmin>851</xmin>
      <ymin>187</ymin>
      <xmax>902</xmax>
      <ymax>230</ymax>
    </bndbox>
  </object>
</annotation>
