<annotation>
  <filename>53--Raid/53_Raid_policeraid_53_206.jpg</filename>
  <size>
    <width>1024</width>
    <height>682</height>
    <depth>3</depth>
  </size>
  <object>
    <name>face</name>
    <pose>Unspecified</pose>
    <truncated>0</truncated>
    <difficult>0</difficult>
    <bndbox>
      <xmin>144</xmin>
      <ymin>340</ymin>
      <xmax>165</xmax>
      <ymax>377</ymax>
    </bndbox>
  </object>
  <object>
    <name>face</name>
    <pose>Unspecified</pose>
    <truncated>0</truncated>
    <difficult>0</difficult>
    <bndbox>
      <xmin>275</xmin>
      <ymin>113</ymin>
      <xmax>307</xmax>
      <ymax>149</ymax>
    </bndbox>
  </object>
  <object>
    <name>face</name>
    <pose>Unspecified</pose>
    <truncated>0</truncated>
    <difficult>0</difficult>
    <bndbox>
      <xmin>356</xmin>
      <ymin>110</ymin>
      <xmax>397</xmax>
      <ymax>138</ymax>
    </bndbox>
  </object>
  <object>
    <name>face</name>
    <pose>Unspecified</pose>
    <truncated>0</truncated>
    <difficult>0</difficult>
    <bndbox>
      <xmin>973</xmin>
      <ymin>299</ymin>
      <xmax>1005</xmax>
      <ymax>324</ymax>
    </bndbox>
  </object>
</annotation>
