<annotation>
  <filename>0_Parade_marchingband_1_941.jpg</filename>
  <size>
    <width>1024</width>
    <height>683</height>
    <depth>3</depth>
  </size>
  <object>
    <name>face</name>
    <pose>Unspecified</pose>
    <truncated>0</truncated>
    <difficult>0</difficult>
    <bndbox>
      <xmin>56</xmin>
      <ymin>246</ymin>
      <xmax>130</xmax>
      <ymax>314</ymax>
    </bndbox>
  </object>
  <object>
    <name>face</name>
    <pose>Unspecified</pose>
    <truncated>0</truncated>
    <difficult>0</difficult>
    <bndbox>
      <xmin>202</xmin>
      <ymin>202</ymin>
      <xmax>290</xmax>
      <ymax>280</ymax>
    </bndbox>
  </object>
  <object>
    <name>face</name>
    <pose>Unspecified</pose>
    <truncated>0</truncated>
    <difficult>0</difficult>
    <bndbox>
      <xmin>440</xmin>
      <ymin>52</ymin>
      <xmax>546</xmax>
      <ymax>136</ymax>
    </bndbox>
  </object>
  <object>
    <name>face</name>
    <pose>Unspecified</pose>
    <truncated>0</truncated>
    <difficult>0</difficult>
    <bndbox>
      <xmin>570</xmin>
      <ymin>184</ymin>
      <xmax>674</xmax>
      <ymax>264</ymax>
    </bndbox>
  </object>
  <object>
    <name>face</name>
    <pose>Unspecified</pose>
    <truncated>0</truncated>
    <difficult>0</difficult>
    <bndbox>
      <xmin>694</xmin>
      <ymin>242</ymin>
      <xmax>794</xmax>
      <ymax>334</ymax>
    </bndbox>
  </object>
</annotation>
