<annotation>
  <filename>12_Group_Team_Organized_Group_12_Group_Team_Organized_Group_12_940.jpg</filename>
  <size>
    <width>1024</width>
    <height>683</height>
    <depth>3</depth>
  </size>
  <object>
    <name>face</name>
    <pose>Unspecified</pose>
    <truncated>0</truncated>
    <difficult>0</difficult>
    <bndbox>
      <xmin>160</xmin>
      <ymin>63</ymin>
      <xmax>225</xmax>
      <ymax>93</ymax>
    </bndbox>
  </object>
  <object>
    <name>face</name>
    <pose>Unspecified</pose>
    <truncated>0</truncated>
    <difficult>0</difficult>
    <bndbox>
      <xmin>282</xmin>
      <ymin>51</ymin>
      <xmax>335</xmax>
      <ymax>73</ymax>
    </bndbox>
  </object>
  <object>
    <name>face</name>
    <pose>Unspecified</pose>
    <truncated>0</truncated>
    <difficult>0</difficult>
    <bndbox>
      <xmin>400</xmin>
      <ymin>99</ymin>
      <xmax>428</xmax>
      <ymax>129</ymax>
    </bndbox>
  </object>
  <object>
    <name>face</name>
    <pose>Unspecified</pose>
    <truncated>0</truncated>
    <difficult>0</difficult>
    <bndbox>
      <xmin>668</xmin>
      <ymin>121</ymin>
      <xmax>687</xmax>
      <ymax>134</ymax>
    </bndbox>
  </object>
  <object>
    <name>face</name>
    <pose>Unspecified</pose>
    <truncated>0</truncated>
    <difficult>0</difficult>
    <bndbox>
      <xmin>682</xmin>
      <ymin>121</ymin>
      <xmax>699</xmax>
      <ymax>130</ymax>
    </bndbox>
  </object>
  <object>
    <name>face</name>
    <pose>Unspecified</pose>
    <truncated>0</truncated>
    <difficult>0</difficult>
    <bndbox>
      <xmin>709</xmin>
      <ymin>112</ymin>
      <xmax>728</xmax>
      <ymax>122</ymax>
    </bndbox>
  </object>
  <object>
    <name>face</name>
    <pose>Unspecified</pose>
    <truncated>0</truncated>
    <difficult>0</difficult>
    <bndbox>
      <xmin>819</xmin>
      <ymin>126</ymin>
      <xmax>831</xmax>
      <ymax>134</ymax>
    </bndbox>
  </object>
  <object>
    <name>face</name>
    <pose>Unspecified</pose>
    <truncated>0</truncated>
    <difficult>0</difficult>
    <bndbox>
      <xmin>774</xmin>
      <ymin>108</ymin>
      <xmax>784</xmax>
      <ymax>113</ymax>
    </bndbox>
  </object>
  <object>
    <name>face</name>
    <pose>Unspecified</pose>
    <truncated>0</truncated>
    <difficult>0</difficult>
    <bndbox>
      <xmin>745</xmin>
      <ymin>119</ymin>
      <xmax>763</xmax>
      <ymax>132</ymax>
    </bndbox>
  </object>
</annotation>
