<annotation>
  <filename>17_Ceremony_Ceremony_17_84.jpg</filename>
  <size>
    <width>1024</width>
    <height>1543</height>
    <depth>3</depth>
  </size>
  <object>
    <name>face</name>
    <pose>Unspecified</pose>
    <truncated>0</truncated>
    <difficult>0</difficult>
    <bndbox>
      <xmin>640</xmin>
      <ymin>255</ymin>
      <xmax>776</xmax>
      <ymax>358</ymax>
    </bndbox>
  </object>
  <object>
    <name>face</name>
    <pose>Unspecified</pose>
    <truncated>0</truncated>
    <difficult>0</difficult>
    <bndbox>
      <xmin>281</xmin>
      <ymin>194</ymin>
      <xmax>424</xmax>
      <ymax>282</ymax>
    </bndbox>
  </object>
  <object>
    <name>face</name>
    <pose>Unspecified</pose>
    <truncated>0</truncated>
    <difficult>0</difficult>
    <bndbox>
      <xmin>136</xmin>
      <ymin>141</ymin>
      <xmax>199</xmax>
      <ymax>200</ymax>
    </bndbox>
  </object>
  <object>
    <name>face</name>
    <pose>Unspecified</pose>
    <truncated>0</truncated>
    <difficult>0</difficult>
    <bndbox>
      <xmin>506</xmin>
      <ymin>156</ymin>
      <xmax>570</xmax>
      <ymax>222</ymax>
    </bndbox>
  </object>
  <object>
    <name>face</name>
    <pose>Unspecified</pose>
    <truncated>0</truncated>
    <difficult>0</difficult>
    <bndbox>
      <xmin>907</xmin>
      <ymin>144</ymin>
      <xmax>985</xmax>
      <ymax>201</ymax>
    </bndbox>
  </object>
</annotation>
