<annotation><filename>20_Family_Group_Family_Group_20_1011.jpg</filename><size><width>1024</width><height>683</height><depth>3</depth></size><segmeneted>0</segmeneted><object><name>face</name><pose>Unspecified</pose><truncated>0</truncated><difficult>0</difficult><bndbox><xmin>184</xmin><ymin>200</ymin><xmax>608</xmax><ymax>534</ymax></bndbox></object><object><name>face</name><pose>Unspecified</pose><truncated>0</truncated><difficult>0</difficult><bndbox><xmin>458</xmin><ymin>120</ymin><xmax>878</xmax><ymax>412</ymax></bndbox></object><object><name>face</name><pose>Unspecified</pose><truncated>0</truncated><difficult>0</difficult><bndbox><xmin>708</xmin><ymin>94</ymin><xmax>1024</xmax><ymax>406</ymax></bndbox></object></annotation>