<annotation><filename>20_Family_Group_Family_Group_20_234.jpg</filename><size><width>1024</width><height>735</height><depth>3</depth></size><segmeneted>0</segmeneted><object><name>face</name><pose>Unspecified</pose><truncated>0</truncated><difficult>0</difficult><bndbox><xmin>211</xmin><ymin>109</ymin><xmax>301</xmax><ymax>173</ymax></bndbox></object><object><name>face</name><pose>Unspecified</pose><truncated>0</truncated><difficult>0</difficult><bndbox><xmin>321</xmin><ymin>146</ymin><xmax>390</xmax><ymax>193</ymax></bndbox></object><object><name>face</name><pose>Unspecified</pose><truncated>0</truncated><difficult>0</difficult><bndbox><xmin>420</xmin><ymin>78</ymin><xmax>500</xmax><ymax>136</ymax></bndbox></object><object><name>face</name><pose>Unspecified</pose><truncated>0</truncated><difficult>0</difficult><bndbox><xmin>601</xmin><ymin>92</ymin><xmax>668</xmax><ymax>146</ymax></bndbox></object><object><name>face</name><pose>Unspecified</pose><truncated>0</truncated><difficult>0</difficult><bndbox><xmin>676</xmin><ymin>123</ymin><xmax>758</xmax><ymax>178</ymax></bndbox></object><object><name>face</name><pose>Unspecified</pose><truncated>0</truncated><difficult>0</difficult><bndbox><xmin>490</xmin><ymin>219</ymin><xmax>575</xmax><ymax>283</ymax></bndbox></object><object><name>face</name><pose>Unspecified</pose><truncated>0</truncated><difficult>0</difficult><bndbox><xmin>304</xmin><ymin>388</ymin><xmax>386</xmax><ymax>452</ymax></bndbox></object><object><name>face</name><pose>Unspecified</pose><truncated>0</truncated><difficult>0</difficult><bndbox><xmin>154</xmin><ymin>259</ymin><xmax>232</xmax><ymax>320</ymax></bndbox></object><object><name>face</name><pose>Unspecified</pose><truncated>0</truncated><difficult>0</difficult><bndbox><xmin>733</xmin><ymin>438</ymin><xmax>805</xmax><ymax>504</ymax></bndbox></object></annotation>