<annotation><filename>21_Festival_Festival_21_974.jpg</filename><size><width>1024</width><height>1553</height><depth>3</depth></size><segmeneted>0</segmeneted><object><name>face</name><pose>Unspecified</pose><truncated>0</truncated><difficult>0</difficult><bndbox><xmin>991</xmin><ymin>174</ymin><xmax>1024</xmax><ymax>206</ymax></bndbox></object><object><name>face</name><pose>Unspecified</pose><truncated>0</truncated><difficult>0</difficult><bndbox><xmin>914</xmin><ymin>139</ymin><xmax>983</xmax><ymax>185</ymax></bndbox></object><object><name>face</name><pose>Unspecified</pose><truncated>0</truncated><difficult>0</difficult><bndbox><xmin>811</xmin><ymin>194</ymin><xmax>886</xmax><ymax>257</ymax></bndbox></object><object><name>face</name><pose>Unspecified</pose><truncated>0</truncated><difficult>0</difficult><bndbox><xmin>821</xmin><ymin>85</ymin><xmax>870</xmax><ymax>133</ymax></bndbox></object><object><name>face</name><pose>Unspecified</pose><truncated>0</truncated><difficult>0</difficult><bndbox><xmin>746</xmin><ymin>94</ymin><xmax>806</xmax><ymax>158</ymax></bndbox></object><object><name>face</name><pose>Unspecified</pose><truncated>0</truncated><difficult>0</difficult><bndbox><xmin>794</xmin><ymin>45</ymin><xmax>832</xmax><ymax>82</ymax></bndbox></object><object><name>face</name><pose>Unspecified</pose><truncated>0</truncated><difficult>0</difficult><bndbox><xmin>831</xmin><ymin>0</ymin><xmax>864</xmax><ymax>36</ymax></bndbox></object><object><name>face</name><pose>Unspecified</pose><truncated>0</truncated><difficult>0</difficult><bndbox><xmin>616</xmin><ymin>0</ymin><xmax>649</xmax><ymax>37</ymax></bndbox></object><object><name>face</name><pose>Unspecified</pose><truncated>0</truncated><difficult>0</difficult><bndbox><xmin>682</xmin><ymin>182</ymin><xmax>742</xmax><ymax>233</ymax></bndbox></object><object><name>face</name><pose>Unspecified</pose><truncated>0</truncated><difficult>0</difficult><bndbox><xmin>557</xmin><ymin>123</ymin><xmax>599</xmax><ymax>162</ymax></bndbox></object><object><name>face</name><pose>Unspecified</pose><truncated>0</truncated><difficult>0</difficult><bndbox><xmin>554</xmin><ymin>201</ymin><xmax>626</xmax><ymax>257</ymax></bndbox></object><object><name>face</name><pose>Unspecified</pose><truncated>0</truncated><difficult>0</difficult><bndbox><xmin>386</xmin><ymin>111</ymin><xmax>535</xmax><ymax>233</ymax></bndbox></object><object><name>face</name><pose>Unspecified</pose><truncated>0</truncated><difficult>0</difficult><bndbox><xmin>300</xmin><ymin>156</ymin><xmax>352</xmax><ymax>201</ymax></bndbox></object><object><name>face</name><pose>Unspecified</pose><truncated>0</truncated><difficult>0</difficult><bndbox><xmin>258</xmin><ymin>237</ymin><xmax>330</xmax><ymax>287</ymax></bndbox></object><object><name>face</name><pose>Unspecified</pose><truncated>0</truncated><difficult>0</difficult><bndbox><xmin>152</xmin><ymin>216</ymin><xmax>217</xmax><ymax>264</ymax></bndbox></object><object><name>face</name><pose>Unspecified</pose><truncated>0</truncated><difficult>0</difficult><bndbox><xmin>62</xmin><ymin>378</ymin><xmax>109</xmax><ymax>432</ymax></bndbox></object></annotation>