<annotation>
  <filename>23_Shoppers_Shoppers_23_695.jpg</filename>
  <size>
    <width>1024</width>
    <height>1540</height>
    <depth>3</depth>
  </size>
  <object>
    <name>face</name>
    <pose>Unspecified</pose>
    <truncated>0</truncated>
    <difficult>0</difficult>
    <bndbox>
      <xmin>900</xmin>
      <ymin>1103</ymin>
      <xmax>907</xmax>
      <ymax>1109</ymax>
    </bndbox>
  </object>
  <object>
    <name>face</name>
    <pose>Unspecified</pose>
    <truncated>0</truncated>
    <difficult>0</difficult>
    <bndbox>
      <xmin>914</xmin>
      <ymin>1113</ymin>
      <xmax>920</xmax>
      <ymax>1117</ymax>
    </bndbox>
  </object>
  <object>
    <name>face</name>
    <pose>Unspecified</pose>
    <truncated>0</truncated>
    <difficult>0</difficult>
    <bndbox>
      <xmin>790</xmin>
      <ymin>1044</ymin>
      <xmax>814</xmax>
      <ymax>1062</ymax>
    </bndbox>
  </object>
  <object>
    <name>face</name>
    <pose>Unspecified</pose>
    <truncated>0</truncated>
    <difficult>0</difficult>
    <bndbox>
      <xmin>790</xmin>
      <ymin>1091</ymin>
      <xmax>832</xmax>
      <ymax>1117</ymax>
    </bndbox>
  </object>
  <object>
    <name>face</name>
    <pose>Unspecified</pose>
    <truncated>0</truncated>
    <difficult>0</difficult>
    <bndbox>
      <xmin>830</xmin>
      <ymin>1112</ymin>
      <xmax>868</xmax>
      <ymax>1139</ymax>
    </bndbox>
  </object>
  <object>
    <name>face</name>
    <pose>Unspecified</pose>
    <truncated>0</truncated>
    <difficult>0</difficult>
    <bndbox>
      <xmin>675</xmin>
      <ymin>1146</ymin>
      <xmax>714</xmax>
      <ymax>1174</ymax>
    </bndbox>
  </object>
  <object>
    <name>face</name>
    <pose>Unspecified</pose>
    <truncated>0</truncated>
    <difficult>0</difficult>
    <bndbox>
      <xmin>232</xmin>
      <ymin>1153</ymin>
      <xmax>262</xmax>
      <ymax>1170</ymax>
    </bndbox>
  </object>
  <object>
    <name>face</name>
    <pose>Unspecified</pose>
    <truncated>0</truncated>
    <difficult>0</difficult>
    <bndbox>
      <xmin>267</xmin>
      <ymin>1104</ymin>
      <xmax>292</xmax>
      <ymax>1122</ymax>
    </bndbox>
  </object>
  <object>
    <name>face</name>
    <pose>Unspecified</pose>
    <truncated>0</truncated>
    <difficult>0</difficult>
    <bndbox>
      <xmin>497</xmin>
      <ymin>1113</ymin>
      <xmax>512</xmax>
      <ymax>1123</ymax>
    </bndbox>
  </object>
  <object>
    <name>face</name>
    <pose>Unspecified</pose>
    <truncated>0</truncated>
    <difficult>0</difficult>
    <bndbox>
      <xmin>522</xmin>
      <ymin>1155</ymin>
      <xmax>534</xmax>
      <ymax>1166</ymax>
    </bndbox>
  </object>
  <object>
    <name>face</name>
    <pose>Unspecified</pose>
    <truncated>0</truncated>
    <difficult>0</difficult>
    <bndbox>
      <xmin>872</xmin>
      <ymin>1104</ymin>
      <xmax>883</xmax>
      <ymax>1108</ymax>
    </bndbox>
  </object>
</annotation>
