<annotation><filename>2_Demonstration_Demonstrators_2_472.jpg</filename><size><width>1024</width><height>683</height><depth>3</depth></size><segmeneted>0</segmeneted><object><name>face</name><pose>Unspecified</pose><truncated>0</truncated><difficult>0</difficult><bndbox><xmin>16</xmin><ymin>260</ymin><xmax>112</xmax><ymax>327</ymax></bndbox></object><object><name>face</name><pose>Unspecified</pose><truncated>0</truncated><difficult>0</difficult><bndbox><xmin>225</xmin><ymin>250</ymin><xmax>256</xmax><ymax>278</ymax></bndbox></object><object><name>face</name><pose>Unspecified</pose><truncated>0</truncated><difficult>0</difficult><bndbox><xmin>315</xmin><ymin>282</ymin><xmax>367</xmax><ymax>319</ymax></bndbox></object><object><name>face</name><pose>Unspecified</pose><truncated>0</truncated><difficult>0</difficult><bndbox><xmin>363</xmin><ymin>225</ymin><xmax>416</xmax><ymax>276</ymax></bndbox></object><object><name>face</name><pose>Unspecified</pose><truncated>0</truncated><difficult>0</difficult><bndbox><xmin>415</xmin><ymin>215</ymin><xmax>486</xmax><ymax>276</ymax></bndbox></object><object><name>face</name><pose>Unspecified</pose><truncated>0</truncated><difficult>0</difficult><bndbox><xmin>485</xmin><ymin>142</ymin><xmax>591</xmax><ymax>214</ymax></bndbox></object><object><name>face</name><pose>Unspecified</pose><truncated>0</truncated><difficult>0</difficult><bndbox><xmin>821</xmin><ymin>285</ymin><xmax>914</xmax><ymax>353</ymax></bndbox></object><object><name>face</name><pose>Unspecified</pose><truncated>0</truncated><difficult>0</difficult><bndbox><xmin>825</xmin><ymin>206</ymin><xmax>880</xmax><ymax>260</ymax></bndbox></object><object><name>face</name><pose>Unspecified</pose><truncated>0</truncated><difficult>0</difficult><bndbox><xmin>757</xmin><ymin>158</ymin><xmax>820</xmax><ymax>205</ymax></bndbox></object><object><name>face</name><pose>Unspecified</pose><truncated>0</truncated><difficult>0</difficult><bndbox><xmin>886</xmin><ymin>218</ymin><xmax>945</xmax><ymax>266</ymax></bndbox></object><object><name>face</name><pose>Unspecified</pose><truncated>0</truncated><difficult>0</difficult><bndbox><xmin>988</xmin><ymin>176</ymin><xmax>1024</xmax><ymax>212</ymax></bndbox></object><object><name>face</name><pose>Unspecified</pose><truncated>0</truncated><difficult>0</difficult><bndbox><xmin>819</xmin><ymin>160</ymin><xmax>879</xmax><ymax>211</ymax></bndbox></object><object><name>face</name><pose>Unspecified</pose><truncated>0</truncated><difficult>0</difficult><bndbox><xmin>883</xmin><ymin>505</ymin><xmax>917</xmax><ymax>542</ymax></bndbox></object><object><name>face</name><pose>Unspecified</pose><truncated>0</truncated><difficult>0</difficult><bndbox><xmin>3</xmin><ymin>221</ymin><xmax>50</xmax><ymax>252</ymax></bndbox></object></annotation>