<annotation>
  <filename>31_Waiter_Waitress_Waiter_Waitress_31_89.jpg</filename>
  <size>
    <width>1024</width>
    <height>1431</height>
    <depth>3</depth>
  </size>
  <object>
    <name>face</name>
    <pose>Unspecified</pose>
    <truncated>0</truncated>
    <difficult>0</difficult>
    <bndbox>
      <xmin>367</xmin>
      <ymin>464</ymin>
      <xmax>457</xmax>
      <ymax>528</ymax>
    </bndbox>
  </object>
  <object>
    <name>face</name>
    <pose>Unspecified</pose>
    <truncated>0</truncated>
    <difficult>0</difficult>
    <bndbox>
      <xmin>641</xmin>
      <ymin>518</ymin>
      <xmax>733</xmax>
      <ymax>582</ymax>
    </bndbox>
  </object>
</annotation>
