<annotation>
  <filename>3_Riot_Riot_3_1017.jpg</filename>
  <size>
    <width>1024</width>
    <height>1029</height>
    <depth>3</depth>
  </size>
  <object>
    <name>face</name>
    <pose>Unspecified</pose>
    <truncated>0</truncated>
    <difficult>0</difficult>
    <bndbox>
      <xmin>42</xmin>
      <ymin>163</ymin>
      <xmax>361</xmax>
      <ymax>464</ymax>
    </bndbox>
  </object>
  <object>
    <name>face</name>
    <pose>Unspecified</pose>
    <truncated>0</truncated>
    <difficult>0</difficult>
    <bndbox>
      <xmin>496</xmin>
      <ymin>632</ymin>
      <xmax>657</xmax>
      <ymax>787</ymax>
    </bndbox>
  </object>
  <object>
    <name>face</name>
    <pose>Unspecified</pose>
    <truncated>0</truncated>
    <difficult>0</difficult>
    <bndbox>
      <xmin>791</xmin>
      <ymin>480</ymin>
      <xmax>938</xmax>
      <ymax>623</ymax>
    </bndbox>
  </object>
</annotation>
