<annotation><filename>40_Gymnastics_Gymnastics_40_674.jpg</filename><size><width>1024</width><height>683</height><depth>3</depth></size><segmeneted>0</segmeneted><object><name>face</name><pose>Unspecified</pose><truncated>0</truncated><difficult>0</difficult><bndbox><xmin>309</xmin><ymin>47</ymin><xmax>376</xmax><ymax>100</ymax></bndbox></object><object><name>face</name><pose>Unspecified</pose><truncated>0</truncated><difficult>0</difficult><bndbox><xmin>441</xmin><ymin>96</ymin><xmax>497</xmax><ymax>149</ymax></bndbox></object><object><name>face</name><pose>Unspecified</pose><truncated>0</truncated><difficult>0</difficult><bndbox><xmin>589</xmin><ymin>78</ymin><xmax>656</xmax><ymax>130</ymax></bndbox></object><object><name>face</name><pose>Unspecified</pose><truncated>0</truncated><difficult>0</difficult><bndbox><xmin>732</xmin><ymin>75</ymin><xmax>796</xmax><ymax>132</ymax></bndbox></object><object><name>face</name><pose>Unspecified</pose><truncated>0</truncated><difficult>0</difficult><bndbox><xmin>679</xmin><ymin>223</ymin><xmax>748</xmax><ymax>282</ymax></bndbox></object><object><name>face</name><pose>Unspecified</pose><truncated>0</truncated><difficult>0</difficult><bndbox><xmin>519</xmin><ymin>249</ymin><xmax>581</xmax><ymax>309</ymax></bndbox></object><object><name>face</name><pose>Unspecified</pose><truncated>0</truncated><difficult>0</difficult><bndbox><xmin>365</xmin><ymin>245</ymin><xmax>432</xmax><ymax>306</ymax></bndbox></object><object><name>face</name><pose>Unspecified</pose><truncated>0</truncated><difficult>0</difficult><bndbox><xmin>222</xmin><ymin>194</ymin><xmax>293</xmax><ymax>252</ymax></bndbox></object><object><name>face</name><pose>Unspecified</pose><truncated>0</truncated><difficult>0</difficult><bndbox><xmin>852</xmin><ymin>403</ymin><xmax>869</xmax><ymax>426</ymax></bndbox></object></annotation>