<annotation><filename>43_Row_Boat_Canoe_43_857.jpg</filename><size><width>1024</width><height>769</height><depth>3</depth></size><segmeneted>0</segmeneted><object><name>face</name><pose>Unspecified</pose><truncated>0</truncated><difficult>0</difficult><bndbox><xmin>803</xmin><ymin>248</ymin><xmax>858</xmax><ymax>283</ymax></bndbox></object><object><name>face</name><pose>Unspecified</pose><truncated>0</truncated><difficult>0</difficult><bndbox><xmin>183</xmin><ymin>222</ymin><xmax>237</xmax><ymax>263</ymax></bndbox></object><object><name>face</name><pose>Unspecified</pose><truncated>0</truncated><difficult>0</difficult><bndbox><xmin>950</xmin><ymin>393</ymin><xmax>1008</xmax><ymax>430</ymax></bndbox></object></annotation>