<annotation>
  <filename>43_Row_Boat_Rowboat_43_681.jpg</filename>
  <size>
    <width>1024</width>
    <height>829</height>
    <depth>3</depth>
  </size>
  <object>
    <name>face</name>
    <pose>Unspecified</pose>
    <truncated>0</truncated>
    <difficult>0</difficult>
    <bndbox>
      <xmin>192</xmin>
      <ymin>279</ymin>
      <xmax>240</xmax>
      <ymax>312</ymax>
    </bndbox>
  </object>
  <object>
    <name>face</name>
    <pose>Unspecified</pose>
    <truncated>0</truncated>
    <difficult>0</difficult>
    <bndbox>
      <xmin>259</xmin>
      <ymin>298</ymin>
      <xmax>303</xmax>
      <ymax>325</ymax>
    </bndbox>
  </object>
  <object>
    <name>face</name>
    <pose>Unspecified</pose>
    <truncated>0</truncated>
    <difficult>0</difficult>
    <bndbox>
      <xmin>682</xmin>
      <ymin>347</ymin>
      <xmax>753</xmax>
      <ymax>396</ymax>
    </bndbox>
  </object>
  <object>
    <name>face</name>
    <pose>Unspecified</pose>
    <truncated>0</truncated>
    <difficult>0</difficult>
    <bndbox>
      <xmin>745</xmin>
      <ymin>417</ymin>
      <xmax>798</xmax>
      <ymax>481</ymax>
    </bndbox>
  </object>
</annotation>
