<annotation><filename>44_Aerobics_Aerobics_44_176.jpg</filename><size><width>1024</width><height>682</height><depth>3</depth></size><segmeneted>0</segmeneted><object><name>face</name><pose>Unspecified</pose><truncated>0</truncated><difficult>0</difficult><bndbox><xmin>961</xmin><ymin>67</ymin><xmax>1017</xmax><ymax>106</ymax></bndbox></object><object><name>face</name><pose>Unspecified</pose><truncated>0</truncated><difficult>0</difficult><bndbox><xmin>623</xmin><ymin>18</ymin><xmax>696</xmax><ymax>65</ymax></bndbox></object><object><name>face</name><pose>Unspecified</pose><truncated>0</truncated><difficult>0</difficult><bndbox><xmin>707</xmin><ymin>132</ymin><xmax>752</xmax><ymax>157</ymax></bndbox></object><object><name>face</name><pose>Unspecified</pose><truncated>0</truncated><difficult>0</difficult><bndbox><xmin>376</xmin><ymin>89</ymin><xmax>433</xmax><ymax>128</ymax></bndbox></object><object><name>face</name><pose>Unspecified</pose><truncated>0</truncated><difficult>0</difficult><bndbox><xmin>4</xmin><ymin>68</ymin><xmax>70</xmax><ymax>122</ymax></bndbox></object><object><name>face</name><pose>Unspecified</pose><truncated>0</truncated><difficult>0</difficult><bndbox><xmin>303</xmin><ymin>90</ymin><xmax>333</xmax><ymax>118</ymax></bndbox></object></annotation>