<annotation>
  <filename>45_Balloonist_Balloonist_45_708.jpg</filename>
  <size>
    <width>1024</width>
    <height>683</height>
    <depth>3</depth>
  </size>
  <object>
    <name>face</name>
    <pose>Unspecified</pose>
    <truncated>0</truncated>
    <difficult>0</difficult>
    <bndbox>
      <xmin>568</xmin>
      <ymin>413</ymin>
      <xmax>591</xmax>
      <ymax>436</ymax>
    </bndbox>
  </object>
  <object>
    <name>face</name>
    <pose>Unspecified</pose>
    <truncated>0</truncated>
    <difficult>0</difficult>
    <bndbox>
      <xmin>471</xmin>
      <ymin>399</ymin>
      <xmax>494</xmax>
      <ymax>419</ymax>
    </bndbox>
  </object>
</annotation>
