<annotation><filename>47_Matador_Bullfighter_Matador_Bullfighter_47_479.jpg</filename><size><width>1024</width><height>808</height><depth>3</depth></size><segmeneted>0</segmeneted><object><name>face</name><pose>Unspecified</pose><truncated>0</truncated><difficult>0</difficult><bndbox><xmin>644</xmin><ymin>304</ymin><xmax>732</xmax><ymax>366</ymax></bndbox></object><object><name>face</name><pose>Unspecified</pose><truncated>0</truncated><difficult>0</difficult><bndbox><xmin>454</xmin><ymin>306</ymin><xmax>556</xmax><ymax>376</ymax></bndbox></object></annotation>