<annotation>
  <filename>48_Parachutist_Paratrooper_Parachutist_Paratrooper_48_352.jpg</filename>
  <size>
    <width>1024</width>
    <height>522</height>
    <depth>3</depth>
  </size>
  <object>
    <name>face</name>
    <pose>Unspecified</pose>
    <truncated>0</truncated>
    <difficult>0</difficult>
    <bndbox>
      <xmin>134</xmin>
      <ymin>26</ymin>
      <xmax>186</xmax>
      <ymax>59</ymax>
    </bndbox>
  </object>
  <object>
    <name>face</name>
    <pose>Unspecified</pose>
    <truncated>0</truncated>
    <difficult>0</difficult>
    <bndbox>
      <xmin>335</xmin>
      <ymin>34</ymin>
      <xmax>381</xmax>
      <ymax>61</ymax>
    </bndbox>
  </object>
  <object>
    <name>face</name>
    <pose>Unspecified</pose>
    <truncated>0</truncated>
    <difficult>0</difficult>
    <bndbox>
      <xmin>899</xmin>
      <ymin>35</ymin>
      <xmax>943</xmax>
      <ymax>66</ymax>
    </bndbox>
  </object>
</annotation>
