<annotation>
  <filename>49_Greeting_peoplegreeting_49_276.jpg</filename>
  <size>
    <width>1024</width>
    <height>721</height>
    <depth>3</depth>
  </size>
  <object>
    <name>face</name>
    <pose>Unspecified</pose>
    <truncated>0</truncated>
    <difficult>0</difficult>
    <bndbox>
      <xmin>734</xmin>
      <ymin>267</ymin>
      <xmax>764</xmax>
      <ymax>294</ymax>
    </bndbox>
  </object>
  <object>
    <name>face</name>
    <pose>Unspecified</pose>
    <truncated>0</truncated>
    <difficult>0</difficult>
    <bndbox>
      <xmin>696</xmin>
      <ymin>295</ymin>
      <xmax>725</xmax>
      <ymax>317</ymax>
    </bndbox>
  </object>
  <object>
    <name>face</name>
    <pose>Unspecified</pose>
    <truncated>0</truncated>
    <difficult>0</difficult>
    <bndbox>
      <xmin>620</xmin>
      <ymin>294</ymin>
      <xmax>654</xmax>
      <ymax>317</ymax>
    </bndbox>
  </object>
  <object>
    <name>face</name>
    <pose>Unspecified</pose>
    <truncated>0</truncated>
    <difficult>0</difficult>
    <bndbox>
      <xmin>673</xmin>
      <ymin>238</ymin>
      <xmax>706</xmax>
      <ymax>264</ymax>
    </bndbox>
  </object>
  <object>
    <name>face</name>
    <pose>Unspecified</pose>
    <truncated>0</truncated>
    <difficult>0</difficult>
    <bndbox>
      <xmin>599</xmin>
      <ymin>245</ymin>
      <xmax>624</xmax>
      <ymax>268</ymax>
    </bndbox>
  </object>
  <object>
    <name>face</name>
    <pose>Unspecified</pose>
    <truncated>0</truncated>
    <difficult>0</difficult>
    <bndbox>
      <xmin>575</xmin>
      <ymin>261</ymin>
      <xmax>606</xmax>
      <ymax>286</ymax>
    </bndbox>
  </object>
</annotation>
