<annotation><filename>51_Dresses_wearingdress_51_171.jpg</filename><size><width>1024</width><height>1527</height><depth>3</depth></size><segmeneted>0</segmeneted><object><name>face</name><pose>Unspecified</pose><truncated>0</truncated><difficult>0</difficult><bndbox><xmin>427</xmin><ymin>393</ymin><xmax>636</xmax><ymax>546</ymax></bndbox></object><object><name>face</name><pose>Unspecified</pose><truncated>0</truncated><difficult>0</difficult><bndbox><xmin>344</xmin><ymin>473</ymin><xmax>417</xmax><ymax>543</ymax></bndbox></object><object><name>face</name><pose>Unspecified</pose><truncated>0</truncated><difficult>0</difficult><bndbox><xmin>106</xmin><ymin>521</ymin><xmax>189</xmax><ymax>586</ymax></bndbox></object><object><name>face</name><pose>Unspecified</pose><truncated>0</truncated><difficult>0</difficult><bndbox><xmin>745</xmin><ymin>614</ymin><xmax>794</xmax><ymax>651</ymax></bndbox></object><object><name>face</name><pose>Unspecified</pose><truncated>0</truncated><difficult>0</difficult><bndbox><xmin>892</xmin><ymin>588</ymin><xmax>934</xmax><ymax>623</ymax></bndbox></object><object><name>face</name><pose>Unspecified</pose><truncated>0</truncated><difficult>0</difficult><bndbox><xmin>968</xmin><ymin>580</ymin><xmax>1007</xmax><ymax>618</ymax></bndbox></object></annotation>