<annotation><filename>52_Photographers_taketouristphotos_52_193.jpg</filename><size><width>1024</width><height>766</height><depth>3</depth></size><segmeneted>0</segmeneted><object><name>face</name><pose>Unspecified</pose><truncated>0</truncated><difficult>0</difficult><bndbox><xmin>393</xmin><ymin>142</ymin><xmax>423</xmax><ymax>168</ymax></bndbox></object><object><name>face</name><pose>Unspecified</pose><truncated>0</truncated><difficult>0</difficult><bndbox><xmin>807</xmin><ymin>117</ymin><xmax>839</xmax><ymax>143</ymax></bndbox></object><object><name>face</name><pose>Unspecified</pose><truncated>0</truncated><difficult>0</difficult><bndbox><xmin>89</xmin><ymin>432</ymin><xmax>114</xmax><ymax>449</ymax></bndbox></object><object><name>face</name><pose>Unspecified</pose><truncated>0</truncated><difficult>0</difficult><bndbox><xmin>87</xmin><ymin>373</ymin><xmax>107</xmax><ymax>384</ymax></bndbox></object></annotation>