<annotation><filename>5_Car_Accident_Car_Crash_5_614.jpg</filename><size><width>1024</width><height>768</height><depth>3</depth></size><segmeneted>0</segmeneted><object><name>face</name><pose>Unspecified</pose><truncated>0</truncated><difficult>0</difficult><bndbox><xmin>296</xmin><ymin>146</ymin><xmax>370</xmax><ymax>178</ymax></bndbox></object><object><name>face</name><pose>Unspecified</pose><truncated>0</truncated><difficult>0</difficult><bndbox><xmin>129</xmin><ymin>223</ymin><xmax>157</xmax><ymax>245</ymax></bndbox></object><object><name>face</name><pose>Unspecified</pose><truncated>0</truncated><difficult>0</difficult><bndbox><xmin>71</xmin><ymin>244</ymin><xmax>89</xmax><ymax>258</ymax></bndbox></object><object><name>face</name><pose>Unspecified</pose><truncated>0</truncated><difficult>0</difficult><bndbox><xmin>20</xmin><ymin>246</ymin><xmax>42</xmax><ymax>265</ymax></bndbox></object><object><name>face</name><pose>Unspecified</pose><truncated>0</truncated><difficult>0</difficult><bndbox><xmin>40</xmin><ymin>247</ymin><xmax>65</xmax><ymax>269</ymax></bndbox></object><object><name>face</name><pose>Unspecified</pose><truncated>0</truncated><difficult>0</difficult><bndbox><xmin>89</xmin><ymin>236</ymin><xmax>110</xmax><ymax>249</ymax></bndbox></object></annotation>