<annotation>
  <filename>12--Group/12_Group_Group_12_Group_Group_12_360.jpg</filename>
  <size>
    <width>1024</width>
    <height>732</height>
    <depth>3</depth>
  </size>
  <object>
    <name>face</name>
    <pose>Unspecified</pose>
    <truncated>0</truncated>
    <difficult>0</difficult>
    <bndbox>
      <xmin>178</xmin>
      <ymin>126</ymin>
      <xmax>262</xmax>
      <ymax>200</ymax>
    </bndbox>
  </object>
  <object>
    <name>face</name>
    <pose>Unspecified</pose>
    <truncated>0</truncated>
    <difficult>0</difficult>
    <bndbox>
      <xmin>440</xmin>
      <ymin>50</ymin>
      <xmax>528</xmax>
      <ymax>112</ymax>
    </bndbox>
  </object>
</annotation>
