<annotation>
  <filename>12--Group/12_Group_Large_Group_12_Group_Large_Group_12_262.jpg</filename>
  <size>
    <width>1024</width>
    <height>683</height>
    <depth>3</depth>
  </size>
  <object>
    <name>face</name>
    <pose>Unspecified</pose>
    <truncated>0</truncated>
    <difficult>0</difficult>
    <bndbox>
      <xmin>116</xmin>
      <ymin>200</ymin>
      <xmax>214</xmax>
      <ymax>282</ymax>
    </bndbox>
  </object>
  <object>
    <name>face</name>
    <pose>Unspecified</pose>
    <truncated>0</truncated>
    <difficult>0</difficult>
    <bndbox>
      <xmin>250</xmin>
      <ymin>148</ymin>
      <xmax>350</xmax>
      <ymax>222</ymax>
    </bndbox>
  </object>
  <object>
    <name>face</name>
    <pose>Unspecified</pose>
    <truncated>0</truncated>
    <difficult>0</difficult>
    <bndbox>
      <xmin>340</xmin>
      <ymin>150</ymin>
      <xmax>436</xmax>
      <ymax>228</ymax>
    </bndbox>
  </object>
  <object>
    <name>face</name>
    <pose>Unspecified</pose>
    <truncated>0</truncated>
    <difficult>0</difficult>
    <bndbox>
      <xmin>446</xmin>
      <ymin>110</ymin>
      <xmax>548</xmax>
      <ymax>184</ymax>
    </bndbox>
  </object>
  <object>
    <name>face</name>
    <pose>Unspecified</pose>
    <truncated>0</truncated>
    <difficult>0</difficult>
    <bndbox>
      <xmin>558</xmin>
      <ymin>158</ymin>
      <xmax>658</xmax>
      <ymax>232</ymax>
    </bndbox>
  </object>
  <object>
    <name>face</name>
    <pose>Unspecified</pose>
    <truncated>0</truncated>
    <difficult>0</difficult>
    <bndbox>
      <xmin>714</xmin>
      <ymin>110</ymin>
      <xmax>814</xmax>
      <ymax>186</ymax>
    </bndbox>
  </object>
  <object>
    <name>face</name>
    <pose>Unspecified</pose>
    <truncated>0</truncated>
    <difficult>0</difficult>
    <bndbox>
      <xmin>836</xmin>
      <ymin>90</ymin>
      <xmax>932</xmax>
      <ymax>164</ymax>
    </bndbox>
  </object>
</annotation>
