<annotation>
  <filename>12--Group/12_Group_Group_12_Group_Group_12_337.jpg</filename>
  <size>
    <width>1024</width>
    <height>765</height>
    <depth>3</depth>
  </size>
  <object>
    <name>face</name>
    <pose>Unspecified</pose>
    <truncated>0</truncated>
    <difficult>0</difficult>
    <bndbox>
      <xmin>220</xmin>
      <ymin>178</ymin>
      <xmax>322</xmax>
      <ymax>256</ymax>
    </bndbox>
  </object>
  <object>
    <name>face</name>
    <pose>Unspecified</pose>
    <truncated>0</truncated>
    <difficult>0</difficult>
    <bndbox>
      <xmin>468</xmin>
      <ymin>288</ymin>
      <xmax>550</xmax>
      <ymax>348</ymax>
    </bndbox>
  </object>
  <object>
    <name>face</name>
    <pose>Unspecified</pose>
    <truncated>0</truncated>
    <difficult>0</difficult>
    <bndbox>
      <xmin>692</xmin>
      <ymin>348</ymin>
      <xmax>772</xmax>
      <ymax>402</ymax>
    </bndbox>
  </object>
</annotation>
