<annotation>
  <filename>37--Soccer/37_Soccer_soccer_ball_37_757.jpg</filename>
  <size>
    <width>1024</width>
    <height>681</height>
    <depth>3</depth>
  </size>
  <object>
    <name>face</name>
    <pose>Unspecified</pose>
    <truncated>0</truncated>
    <difficult>0</difficult>
    <bndbox>
      <xmin>788</xmin>
      <ymin>270</ymin>
      <xmax>888</xmax>
      <ymax>350</ymax>
    </bndbox>
  </object>
  <object>
    <name>face</name>
    <pose>Unspecified</pose>
    <truncated>0</truncated>
    <difficult>0</difficult>
    <bndbox>
      <xmin>242</xmin>
      <ymin>272</ymin>
      <xmax>304</xmax>
      <ymax>336</ymax>
    </bndbox>
  </object>
</annotation>
