<annotation>
  <filename>51--Dresses/51_Dresses_wearingdress_51_503.jpg</filename>
  <size>
    <width>1024</width>
    <height>1180</height>
    <depth>3</depth>
  </size>
  <object>
    <name>face</name>
    <pose>Unspecified</pose>
    <truncated>0</truncated>
    <difficult>0</difficult>
    <bndbox>
      <xmin>193</xmin>
      <ymin>64</ymin>
      <xmax>331</xmax>
      <ymax>156</ymax>
    </bndbox>
  </object>
  <object>
    <name>face</name>
    <pose>Unspecified</pose>
    <truncated>0</truncated>
    <difficult>0</difficult>
    <bndbox>
      <xmin>782</xmin>
      <ymin>18</ymin>
      <xmax>911</xmax>
      <ymax>99</ymax>
    </bndbox>
  </object>
</annotation>
